universal_set_transformers-0.1.0.dist-info/licenses/LICENSE
ust/__init__.py
ust/layers.py
ust/modules_old.py
ust/utils.py
ust/api/modules.py
ust/api/types.py
ust/modules/__init__.py
ust/modules/scaled_dot_product_attention.py
ust/modules/set_transformer.py
universal_set_transformers-0.1.0.dist-info/METADATA
universal_set_transformers-0.1.0.dist-info/WHEEL
universal_set_transformers-0.1.0.dist-info/top_level.txt
universal_set_transformers-0.1.0.dist-info/RECORD
