Metadata-Version: 2.4
Name: universal-set-transformers
Version: 0.1.0
Summary: Universal Set Transformers for scalable set/multiset modeling
Author-email: "David W. Ludwig II" <davidludwigii@gmail.com>
License: Copyright 2025 David W. Ludwig II
Project-URL: Homepage, https://github.com/DLii-Research/universal-set-transformers
Project-URL: Bug Tracker, https://github.com/DLii-Research/universal-set-transformers/issues
Requires-Python: >=3.8
License-File: LICENSE
Requires-Dist: torch>=2.5.1
Provides-Extra: dev
Requires-Dist: torchvision>=0.20.1; extra == "dev"
Requires-Dist: torch_geometric>=2.5.1; extra == "dev"
Dynamic: license-file
